[
  {
    "date": "2026-03-17",
    "scrip_code": "522205",
    "symbol": "PRAJIND",
    "company": "Praj Industries Ltd.",
    "sector": "Capital Goods",
    "industry": "Industrial Manufacturing",
    "group": "A",
    "market_cap_category": "Micro Cap",
    "section": "Analyst / Investor Meets",
    "subcategory": "Analyst / Investor Meet",
    "clean_headline": "ASK Automotive Limited scheduled institutional investor and analyst meetings",
    "raw_headline": "Intimation regarding participation in Investor Conference.",
    "is_critical": false,
    "attachment": "d5be2890-d8dc-48f8-bc55-4f125e12cc37.pdf"
  }
]