[
  {
    "date": "2026-03-17",
    "scrip_code": "530073",
    "symbol": "SANGHVIMOV",
    "company": "Sanghvi Movers Ltd.",
    "sector": "Services",
    "industry": "Commercial Services & Supplies",
    "group": "B",
    "market_cap_category": "Micro Cap",
    "section": "Operational Alerts",
    "subcategory": "Analyst / Investor Meet",
    "clean_headline": "Telephone Cables Limited Corporate Insolvency Resolution Process commenced by NCLT order dated February 19, 2026",
    "raw_headline": "Intimation of Schedule of Analyst/Institutional Investors Meet to be held on March 23, 2026.",
    "is_critical": false,
    "attachment": "0aec4ec1-1b95-4abe-b7ca-f7b4a47da5b5.pdf"
  }
]