[
  {
    "date": "2026-03-19",
    "scrip_code": "544111",
    "symbol": "PARKHOTELS",
    "company": "Apeejay Surrendra Park Hotels Limited",
    "sector": "Consumer Services",
    "industry": "Leisure Services",
    "group": "B",
    "market_cap_category": "Micro Cap",
    "section": "Management Changes",
    "subcategory": "General",
    "clean_headline": "Senior managerial personnel resigned from the company.",
    "raw_headline": "Press Release on THE Lotus Palace Chettinad to host Kalai- an Art and Architecture Festival at Chetttinad, Tamil Nadu",
    "is_critical": false,
    "attachment": "78b2245f-435a-4607-b0a7-449b59ee2ae3.pdf"
  },
  {
    "date": "2026-03-19",
    "scrip_code": "544111",
    "symbol": "PARKHOTELS",
    "company": "Apeejay Surrendra Park Hotels Limited",
    "sector": "Consumer Services",
    "industry": "Leisure Services",
    "group": "B",
    "market_cap_category": "Micro Cap",
    "section": "Management Changes",
    "subcategory": "General",
    "clean_headline": "Ms. Neha Vaswani appointed as Finance Head - Digital at Balaji Telefilms",
    "raw_headline": "Intimation under Regulation 7(2)(b) of SEBI (Prohibition of Insider Trading) Regulations, 2015",
    "is_critical": false,
    "attachment": "39f62112-8151-468f-abb6-889f36bfe6b9.pdf"
  }
]