[
  {
    "date": "2026-03-12",
    "scrip_code": "500380",
    "symbol": "JKLAKSHMI",
    "company": "JK Lakshmi Cement Limited",
    "sector": "Construction Materials",
    "industry": "Cement & Cement Products",
    "group": "A",
    "market_cap_category": "Micro Cap",
    "section": "Acquisitions & M&A",
    "subcategory": "Acquisition",
    "clean_headline": "",
    "raw_headline": "Intimation under Regulation 30 of the SEBI (Listing Obligations and Disclosure Requirements) Regulations, 2015",
    "is_critical": true,
    "attachment": "512360a2-4575-4923-88b3-85ac64f059b4.pdf"
  },
  {
    "date": "2026-03-12",
    "scrip_code": "500380",
    "symbol": "JKLAKSHMI",
    "company": "JK Lakshmi Cement Limited",
    "sector": "Construction Materials",
    "industry": "Cement & Cement Products",
    "group": "A",
    "market_cap_category": "Micro Cap",
    "section": "Analyst / Investor Meets",
    "subcategory": "General",
    "clean_headline": "Carraro India scheduled analyst and investor meeting at Pune facilities on 18th March 2026",
    "raw_headline": "Pursuant to Regulation 30 of the Securities and Exchange Board of India (Listing Obligations and Disclosure Requirements) Regulations, 2015, the Company has been declared as the ''Preferred ....",
    "is_critical": false,
    "attachment": "1c96b6da-e970-4a7e-aa9f-5991709f0238.pdf"
  },
  {
    "date": "2026-03-13",
    "scrip_code": "500380",
    "symbol": "JKLAKSHMI",
    "company": "JK Lakshmi Cement Limited",
    "sector": "Construction Materials",
    "industry": "Cement & Cement Products",
    "group": "A",
    "market_cap_category": "Micro Cap",
    "section": "Mergers & Schemes",
    "subcategory": "General",
    "clean_headline": "Mercantile Ventures shareholders meeting held pursuant to NCLT order on Scheme of Arrangement",
    "raw_headline": "Pursuant to Regulation 30 of the Securities and Exchange Board of India (Listing Obligations and Disclosure Requirements) Regulations, 2015, the Company has been declared as the \"Preferred ....",
    "is_critical": false,
    "attachment": "ab5a12ce-94c1-4404-a098-3defdf637d22.pdf"
  }
]