[
  {
    "date": "2026-03-16",
    "scrip_code": "534532",
    "symbol": "LYPSAGEMS",
    "company": "Lypsa Gems & Jewellery Limited",
    "sector": "Consumer Durables",
    "industry": "Consumer Durables",
    "group": "B",
    "market_cap_category": "Micro Cap",
    "section": "AGM / EGM / Postal Ballot",
    "subcategory": "Postal Ballot",
    "clean_headline": "Postal Ballot along with Scrutinizer Report",
    "raw_headline": "Postal Ballot along with Scrutinizer Report",
    "is_critical": false,
    "attachment": "625dbb44-555d-4148-9302-c9d6cb36e1e7.pdf"
  },
  {
    "date": "2026-03-16",
    "scrip_code": "534532",
    "symbol": "LYPSAGEMS",
    "company": "Lypsa Gems & Jewellery Limited",
    "sector": "Consumer Durables",
    "industry": "Consumer Durables",
    "group": "B",
    "market_cap_category": "Micro Cap",
    "section": "AGM / EGM / Postal Ballot",
    "subcategory": "Postal Ballot",
    "clean_headline": "Postal Ballot along with Scrutinizer Report",
    "raw_headline": "Postal Ballot along with Scrutinizer Report",
    "is_critical": false,
    "attachment": "625dbb44-555d-4148-9302-c9d6cb36e1e7.pdf"
  }
]