[
  {
    "date": "2026-03-13",
    "scrip_code": "540776",
    "symbol": "5PAISA",
    "company": "5paisa Capital Limited",
    "sector": "Financial Services",
    "industry": "Capital Markets",
    "group": "B",
    "market_cap_category": "Micro Cap",
    "section": "AGM / EGM / Postal Ballot",
    "subcategory": "General",
    "clean_headline": "Proceedings and outcome of the 3rd Extraordinary General Meeting of the company held on March 13, 2026.",
    "raw_headline": "Announcement under Regulation 30 of SEBI (Listing Obligations and Disclosure Requirements) Regulation, 2015",
    "is_critical": false,
    "attachment": "d4aeba91-4e23-4303-a63e-5941e48771a7.pdf"
  },
  {
    "date": "2026-03-13",
    "scrip_code": "540776",
    "symbol": "5PAISA",
    "company": "5paisa Capital Limited",
    "sector": "Financial Services",
    "industry": "Capital Markets",
    "group": "B",
    "market_cap_category": "Micro Cap",
    "section": "Management Changes",
    "subcategory": "General",
    "clean_headline": "Lime Chemicals Ltd appointed an Independent Director",
    "raw_headline": "Announcement under Regulation 30 of SEBI (Listing Obligations and Disclosure Requirements) Regulation, 2015",
    "is_critical": false,
    "attachment": "d4aeba91-4e23-4303-a63e-5941e48771a7.pdf"
  }
]