[
  {
    "date": "2026-03-16",
    "scrip_code": "532370",
    "symbol": "RAMCOSYS",
    "company": "Ramco Systems Ltd",
    "sector": "Information Technology",
    "industry": "IT - Software",
    "group": "B",
    "market_cap_category": "Micro Cap",
    "section": "Operations & Capacity",
    "subcategory": "Press Release / Media Release",
    "clean_headline": "Mayank Cattle Food Limited launched two new products: MAYANK ALL IN ONE and MAYANK HAJMA HAJAM.",
    "raw_headline": "Press Release titled \"Anna University and Ramco Systems Sign MOU to Establish an Intelligent ERP Lab for Industrial Engineering Students\"",
    "is_critical": false,
    "attachment": "371955cb-ce57-4922-b850-118bf791626b.pdf"
  },
  {
    "date": "2026-03-16",
    "scrip_code": "532370",
    "symbol": "RAMCOSYS",
    "company": "Ramco Systems Ltd",
    "sector": "Information Technology",
    "industry": "IT - Software",
    "group": "B",
    "market_cap_category": "Micro Cap",
    "section": "Press Releases",
    "subcategory": "Press Release / Media Release",
    "clean_headline": "Goodluck Defence and Aerospace Limited successfully commenced first overseas dispatch of USD 6 million order for 155mm heavy calibre empty shells.",
    "raw_headline": "Press Release titled \"Anna University and Ramco Systems Sign MOU to Establish an Intelligent ERP Lab for Industrial Engineering Students\"",
    "is_critical": false,
    "attachment": "371955cb-ce57-4922-b850-118bf791626b.pdf"
  }
]