[
  {
    "date": "2026-03-17",
    "scrip_code": "533482",
    "symbol": "KRIDHANINF",
    "company": "Kridhan Infra Limited",
    "sector": "Construction",
    "industry": "Construction",
    "group": "B",
    "market_cap_category": "Micro Cap",
    "section": "Mergers & Schemes",
    "subcategory": "Allotment of Equity Shares",
    "clean_headline": "Scheme of Amalgamation between U R Energy (India) Private Limited and Jhaveri Credits and Capital Limited under Sections 230-232 of Companies Act",
    "raw_headline": "Announcement under Regulation 30 (LODR) - Allotment",
    "is_critical": false,
    "attachment": "7f541878-e2e1-450e-8eaa-453f74927614.pdf"
  }
]