[
  {
    "date": "2026-03-12",
    "scrip_code": "504973",
    "symbol": "CHOLAHLDNG",
    "company": "CHOLAMANDALAM FINANCIAL HOLDINGS LIMITED",
    "sector": "Financial Services",
    "industry": "Finance",
    "group": "A",
    "market_cap_category": "Small Cap",
    "section": "Credit Ratings",
    "subcategory": "Credit Rating",
    "clean_headline": "",
    "raw_headline": "Cholamandalam Financial Holdings Limited has informed the exchange regarding credit rating.",
    "is_critical": true,
    "attachment": "7c70f25e-cbe7-4466-8091-b37261f75e0b.pdf"
  }
]